async_retrying_ng/__init__.py
async_retrying_ng/version.py
async_retrying_ng-0.1.3.dist-info/LICENSE
async_retrying_ng-0.1.3.dist-info/METADATA
async_retrying_ng-0.1.3.dist-info/WHEEL
async_retrying_ng-0.1.3.dist-info/RECORD
