Metadata-Version: 2.1
Name: async-retrying-ng
Version: 0.1.3
Summary: Next Gen. simple retrying for asyncio.
License: MIT
Author: Malene Trab
Author-email: malene@trab.dk
Requires-Python: >=3.10,<4.0
Classifier: License :: OSI Approved :: MIT License
Classifier: Programming Language :: Python :: 3
Classifier: Programming Language :: Python :: 3.10
Classifier: Programming Language :: Python :: 3.11
Classifier: Topic :: Software Development :: Libraries :: Python Modules
Requires-Dist: async-timeout (>=4.0.2)
Project-URL: Documentation, https://github.com/mtrab/async_retrying_ng
